{
  "_hallucinatedQuestions": [],
  "HUMAN": {
    "node_99|node_100": {
      "traversable": true,
      "note": "Auto-approved: able-bodied human",
      "timestamp": "2025-11-04T21:26:53.054Z"
    },
    "node_100|node_101": {
      "traversable": true,
      "note": "",
      "timestamp": "2025-11-04T21:38:33.002Z",
      "question": "Can [Agent] move from the gray sectional sofa in the Main living room and kitchen to the large bed in the Master bedroom?"
    },
    "node_101|node_103": {
      "traversable": true,
      "note": "",
      "timestamp": "2025-11-04T21:38:39.295Z",
      "question": "Can [Agent] move from the gray sectional sofa in the Main living room and kitchen to the large bed in the Master bedroom?"
    },
    "node_100|node_104": {
      "traversable": true,
      "note": "",
      "timestamp": "2025-11-04T21:38:44.282Z",
      "question": "Can [Agent] move from the gray sectional sofa in the Main living room and kitchen to the large bed in the Master bedroom?"
    },
    "node_104|node_105": {
      "traversable": true,
      "note": "",
      "timestamp": "2025-11-04T21:38:50.803Z",
      "question": "Can [Agent] move from the gray sectional sofa in the Main living room and kitchen to the large bed in the Master bedroom?"
    },
    "node_105|node_101": {
      "traversable": true,
      "note": "",
      "timestamp": "2025-11-04T21:38:55.617Z",
      "question": "Can [Agent] move from the gray sectional sofa in the Main living room and kitchen to the large bed in the Master bedroom?"
    },
    "node_101|node_107": {
      "traversable": true,
      "note": "",
      "timestamp": "2025-11-04T21:43:55.898Z",
      "question": "Can [Agent] move from the main double doors in the Entrance foyer and hallway to the computer desk in the Home office next to entrance?"
    },
    "node_103|node_106": {
      "traversable": true,
      "note": "",
      "timestamp": "2025-11-04T21:44:09.576Z",
      "question": "Can [Agent] move from the dresser with a mirror in the Master bedroom to the large corner tub in the Master bedroom bathroom?"
    },
    "node_101|node_105": {
      "traversable": true,
      "note": "",
      "timestamp": "2025-11-04T21:44:50.027Z",
      "question": "Can [Agent] move from the refrigerator in the Main living room and kitchen to the sofa in the Smaller living room with sofa?"
    },
    "node_101|node_108": {
      "traversable": true,
      "note": "",
      "timestamp": "2025-11-04T21:45:03.601Z",
      "question": "Can [Agent] move from the bottom of the stairs in the Entrance foyer and hallway to the top of the stairs at the Second floor stair landing and hallway?"
    },
    "node_108|node_110": {
      "traversable": true,
      "note": "",
      "timestamp": "2025-11-04T21:45:26.041Z",
      "question": "Can [Agent] move from the central railing on the landing in the Second floor stair landing and hallway to the bed with pink sheets in the Bedroom with pink sheets?"
    },
    "node_109|node_108": {
      "traversable": true,
      "note": "",
      "timestamp": "2025-11-04T21:45:40.573Z",
      "question": "Can [Agent] move from the office chair in the Second floor home office to the bed with stripe sheets in the Bedroom with stripe sheets?"
    },
    "node_108|node_111": {
      "traversable": true,
      "note": "",
      "timestamp": "2025-11-04T21:45:44.253Z",
      "question": "Can [Agent] move from the office chair in the Second floor home office to the bed with stripe sheets in the Bedroom with stripe sheets?"
    },
    "node_115|node_108": {
      "traversable": true,
      "note": "",
      "timestamp": "2025-11-04T21:47:18.398Z",
      "question": "Can [Agent] move from the bed with the gray headboard in the Bedroom with gray wall to the vanity in the Bathroom between two bedrooms?"
    },
    "node_108|node_116": {
      "traversable": true,
      "note": "",
      "timestamp": "2025-11-04T21:47:24.023Z",
      "question": "Can [Agent] move from the bed with the gray headboard in the Bedroom with gray wall to the vanity in the Bathroom between two bedrooms?"
    },
    "node_116|node_114": {
      "traversable": true,
      "note": "",
      "timestamp": "2025-11-04T21:47:33.903Z",
      "question": "Can [Agent] move from the bed with the gray headboard in the Bedroom with gray wall to the vanity in the Bathroom between two bedrooms?"
    },
    "node_115|node_114": {
      "traversable": true,
      "note": "",
      "timestamp": "2025-11-04T21:47:36.743Z",
      "question": "Can [Agent] move from the bed with the gray headboard in the Bedroom with gray wall to the vanity in the Bathroom between two bedrooms?"
    },
    "node_111|node_108": {
      "traversable": true,
      "note": "",
      "timestamp": "2025-11-04T21:51:00.549Z",
      "question": "Can [Agent] move from the dresser with a mirror in the Bedroom with stripe sheets to the toilet in the Second floor shared bathroom with red rug?"
    },
    "node_108|node_113": {
      "traversable": true,
      "note": "Auto-approved: able-bodied human",
      "timestamp": "2025-11-04T21:51:39.788Z"
    },
    "node_113|node_111": {
      "traversable": true,
      "note": "Auto-approved: able-bodied human",
      "timestamp": "2025-11-04T21:51:39.788Z"
    },
    "node_111|node_113": {
      "traversable": true,
      "note": "",
      "timestamp": "2025-11-04T21:53:00.820Z",
      "question": "Can [Agent] move from the dresser with a mirror in the Bedroom with stripe sheets to the toilet in the Second floor shared bathroom with red rug?"
    },
    "node_110|node_108": {
      "traversable": true,
      "note": "",
      "timestamp": "2025-11-04T21:53:41.699Z",
      "question": "Can [Agent] move from the wall-mounted TV in the Bedroom with pink sheets to the main stairwell opening in the Second floor stair landing and hallway?"
    }
  },
  "WHEELCHAIR": {
    "node_99|node_100": {
      "traversable": false,
      "note": "door sill",
      "timestamp": "2025-11-04T21:38:03.338Z",
      "question": "Can [Agent] move from the BBQ grill area on the Patio and yard to the kitchen island with a sink in the Main living room and kitchen?"
    },
    "node_100|node_101": {
      "traversable": true,
      "note": "",
      "timestamp": "2025-11-04T21:40:00.465Z",
      "question": "Can [Agent] move from the gray sectional sofa in the Main living room and kitchen to the large bed in the Master bedroom?"
    },
    "node_101|node_103": {
      "traversable": true,
      "note": "",
      "timestamp": "2025-11-04T21:40:09.146Z",
      "question": "Can [Agent] move from the gray sectional sofa in the Main living room and kitchen to the large bed in the Master bedroom?"
    },
    "node_100|node_104": {
      "traversable": true,
      "note": "",
      "timestamp": "2025-11-04T21:40:44.811Z",
      "question": "Can [Agent] move from the gray sectional sofa in the Main living room and kitchen to the large bed in the Master bedroom?"
    },
    "node_104|node_105": {
      "traversable": true,
      "note": "",
      "timestamp": "2025-11-04T21:40:48.171Z",
      "question": "Can [Agent] move from the gray sectional sofa in the Main living room and kitchen to the large bed in the Master bedroom?"
    },
    "node_105|node_101": {
      "traversable": true,
      "note": "",
      "timestamp": "2025-11-04T21:40:50.650Z",
      "question": "Can [Agent] move from the gray sectional sofa in the Main living room and kitchen to the large bed in the Master bedroom?"
    },
    "node_101|node_107": {
      "traversable": true,
      "note": "",
      "timestamp": "2025-11-04T21:43:59.790Z",
      "question": "Can [Agent] move from the main double doors in the Entrance foyer and hallway to the computer desk in the Home office next to entrance?"
    },
    "node_103|node_106": {
      "traversable": true,
      "note": "",
      "timestamp": "2025-11-04T21:44:10.670Z",
      "question": "Can [Agent] move from the dresser with a mirror in the Master bedroom to the large corner tub in the Master bedroom bathroom?"
    },
    "node_101|node_105": {
      "traversable": true,
      "note": "",
      "timestamp": "2025-11-04T21:44:52.841Z",
      "question": "Can [Agent] move from the refrigerator in the Main living room and kitchen to the sofa in the Smaller living room with sofa?"
    },
    "node_101|node_108": {
      "traversable": false,
      "note": "cannot go up/down stairs",
      "timestamp": "2025-11-04T21:45:14.375Z",
      "question": "Can [Agent] move from the bottom of the stairs in the Entrance foyer and hallway to the top of the stairs at the Second floor stair landing and hallway?"
    },
    "node_108|node_110": {
      "traversable": true,
      "note": "",
      "timestamp": "2025-11-04T21:45:31.174Z",
      "question": "Can [Agent] move from the central railing on the landing in the Second floor stair landing and hallway to the bed with pink sheets in the Bedroom with pink sheets?"
    },
    "node_109|node_108": {
      "traversable": true,
      "note": "",
      "timestamp": "2025-11-04T21:45:46.014Z",
      "question": "Can [Agent] move from the office chair in the Second floor home office to the bed with stripe sheets in the Bedroom with stripe sheets?"
    },
    "node_108|node_111": {
      "traversable": true,
      "note": "",
      "timestamp": "2025-11-04T21:45:47.546Z",
      "question": "Can [Agent] move from the office chair in the Second floor home office to the bed with stripe sheets in the Bedroom with stripe sheets?"
    },
    "node_115|node_108": {
      "traversable": true,
      "note": "",
      "timestamp": "2025-11-04T21:49:52.165Z",
      "question": "Can [Agent] move from the bed with the gray headboard in the Bedroom with gray wall to the vanity in the Bathroom between two bedrooms?"
    },
    "node_108|node_116": {
      "traversable": true,
      "note": "",
      "timestamp": "2025-11-04T21:49:54.445Z",
      "question": "Can [Agent] move from the bed with the gray headboard in the Bedroom with gray wall to the vanity in the Bathroom between two bedrooms?"
    },
    "node_116|node_114": {
      "traversable": true,
      "note": "",
      "timestamp": "2025-11-04T21:50:22.471Z",
      "question": "Can [Agent] move from the bed with the gray headboard in the Bedroom with gray wall to the vanity in the Bathroom between two bedrooms?"
    },
    "node_115|node_114": {
      "traversable": true,
      "note": "",
      "timestamp": "2025-11-04T21:50:25.189Z",
      "question": "Can [Agent] move from the bed with the gray headboard in the Bedroom with gray wall to the vanity in the Bathroom between two bedrooms?"
    },
    "node_108|node_113": {
      "traversable": true,
      "note": "",
      "timestamp": "2025-11-04T21:51:55.507Z",
      "question": "Can [Agent] move from the office chair in the Second floor home office to the bed with stripe sheets in the Bedroom with stripe sheets?"
    },
    "node_113|node_111": {
      "traversable": true,
      "note": "",
      "timestamp": "2025-11-04T21:52:15.100Z",
      "question": "Can [Agent] move from the office chair in the Second floor home office to the bed with stripe sheets in the Bedroom with stripe sheets?"
    },
    "node_111|node_108": {
      "traversable": true,
      "note": "",
      "timestamp": "2025-11-04T21:53:02.860Z",
      "question": "Can [Agent] move from the dresser with a mirror in the Bedroom with stripe sheets to the toilet in the Second floor shared bathroom with red rug?"
    },
    "node_111|node_113": {
      "traversable": true,
      "note": "",
      "timestamp": "2025-11-04T21:53:09.459Z",
      "question": "Can [Agent] move from the dresser with a mirror in the Bedroom with stripe sheets to the toilet in the Second floor shared bathroom with red rug?"
    },
    "node_110|node_108": {
      "traversable": true,
      "note": "",
      "timestamp": "2025-11-04T21:53:44.151Z",
      "question": "Can [Agent] move from the wall-mounted TV in the Bedroom with pink sheets to the main stairwell opening in the Second floor stair landing and hallway?"
    }
  },
  "ROBOT": {
    "node_99|node_100": {
      "traversable": false,
      "note": "door too narrow",
      "timestamp": "2025-11-04T21:38:12.110Z",
      "question": "Can [Agent] move from the BBQ grill area on the Patio and yard to the kitchen island with a sink in the Main living room and kitchen?"
    },
    "node_100|node_101": {
      "traversable": true,
      "note": "",
      "timestamp": "2025-11-04T21:41:18.889Z",
      "question": "Can [Agent] move from the gray sectional sofa in the Main living room and kitchen to the large bed in the Master bedroom?"
    },
    "node_101|node_103": {
      "traversable": true,
      "note": "",
      "timestamp": "2025-11-04T21:41:25.342Z",
      "question": "Can [Agent] move from the gray sectional sofa in the Main living room and kitchen to the large bed in the Master bedroom?"
    },
    "node_100|node_104": {
      "traversable": true,
      "note": "",
      "timestamp": "2025-11-04T21:43:06.913Z",
      "question": "Can [Agent] move from the gray sectional sofa in the Main living room and kitchen to the large bed in the Master bedroom?"
    },
    "node_104|node_105": {
      "traversable": true,
      "note": "",
      "timestamp": "2025-11-04T21:43:31.192Z",
      "question": "Can [Agent] move from the gray sectional sofa in the Main living room and kitchen to the large bed in the Master bedroom?"
    },
    "node_105|node_101": {
      "traversable": true,
      "note": "",
      "timestamp": "2025-11-04T21:43:33.458Z",
      "question": "Can [Agent] move from the gray sectional sofa in the Main living room and kitchen to the large bed in the Master bedroom?"
    },
    "node_101|node_107": {
      "traversable": true,
      "note": "",
      "timestamp": "2025-11-04T21:44:01.018Z",
      "question": "Can [Agent] move from the main double doors in the Entrance foyer and hallway to the computer desk in the Home office next to entrance?"
    },
    "node_103|node_106": {
      "traversable": false,
      "note": "door too narrow",
      "timestamp": "2025-11-04T21:44:41.497Z",
      "question": "Can [Agent] move from the dresser with a mirror in the Master bedroom to the large corner tub in the Master bedroom bathroom?"
    },
    "node_101|node_105": {
      "traversable": true,
      "note": "",
      "timestamp": "2025-11-04T21:44:54.148Z",
      "question": "Can [Agent] move from the refrigerator in the Main living room and kitchen to the sofa in the Smaller living room with sofa?"
    },
    "node_101|node_108": {
      "traversable": false,
      "note": "cannot go up/down stairs",
      "timestamp": "2025-11-04T21:45:17.002Z",
      "question": "Can [Agent] move from the bottom of the stairs in the Entrance foyer and hallway to the top of the stairs at the Second floor stair landing and hallway?"
    },
    "node_108|node_110": {
      "traversable": false,
      "note": "door too narrow",
      "timestamp": "2025-11-04T21:45:36.254Z",
      "question": "Can [Agent] move from the central railing on the landing in the Second floor stair landing and hallway to the bed with pink sheets in the Bedroom with pink sheets?"
    },
    "node_109|node_108": {
      "traversable": true,
      "note": "",
      "timestamp": "2025-11-04T21:45:48.519Z",
      "question": "Can [Agent] move from the office chair in the Second floor home office to the bed with stripe sheets in the Bedroom with stripe sheets?"
    },
    "node_108|node_111": {
      "traversable": false,
      "note": "door too narrow",
      "timestamp": "2025-11-04T21:45:57.908Z",
      "question": "Can [Agent] move from the office chair in the Second floor home office to the bed with stripe sheets in the Bedroom with stripe sheets?"
    },
    "node_115|node_108": {
      "traversable": false,
      "note": "door too narrow",
      "timestamp": "2025-11-04T21:50:36.523Z",
      "question": "Can [Agent] move from the bed with the gray headboard in the Bedroom with gray wall to the vanity in the Bathroom between two bedrooms?"
    },
    "node_108|node_116": {
      "traversable": false,
      "note": "door too narrow",
      "timestamp": "2025-11-04T21:50:38.643Z",
      "question": "Can [Agent] move from the bed with the gray headboard in the Bedroom with gray wall to the vanity in the Bathroom between two bedrooms?"
    },
    "node_116|node_114": {
      "traversable": false,
      "note": "door too narrow",
      "timestamp": "2025-11-04T21:50:40.096Z",
      "question": "Can [Agent] move from the bed with the gray headboard in the Bedroom with gray wall to the vanity in the Bathroom between two bedrooms?"
    },
    "node_115|node_114": {
      "traversable": false,
      "note": "door too narrow",
      "timestamp": "2025-11-04T21:50:43.390Z",
      "question": "Can [Agent] move from the bed with the gray headboard in the Bedroom with gray wall to the vanity in the Bathroom between two bedrooms?"
    },
    "node_108|node_113": {
      "traversable": false,
      "note": "door too narrow",
      "timestamp": "2025-11-04T21:53:20.660Z",
      "question": "Can [Agent] move from the dresser with a mirror in the Bedroom with stripe sheets to the toilet in the Second floor shared bathroom with red rug?"
    },
    "node_113|node_111": {
      "traversable": false,
      "note": "door too narrow",
      "timestamp": "2025-11-04T21:52:29.394Z",
      "question": "Can [Agent] move from the office chair in the Second floor home office to the bed with stripe sheets in the Bedroom with stripe sheets?"
    },
    "node_111|node_108": {
      "traversable": false,
      "note": "door too narrow",
      "timestamp": "2025-11-04T21:53:17.407Z",
      "question": "Can [Agent] move from the dresser with a mirror in the Bedroom with stripe sheets to the toilet in the Second floor shared bathroom with red rug?"
    },
    "node_111|node_113": {
      "traversable": false,
      "note": "door too narrow",
      "timestamp": "2025-11-04T21:53:22.060Z",
      "question": "Can [Agent] move from the dresser with a mirror in the Bedroom with stripe sheets to the toilet in the Second floor shared bathroom with red rug?"
    },
    "node_110|node_108": {
      "traversable": false,
      "note": "door too narrow",
      "timestamp": "2025-11-04T21:53:45.805Z",
      "question": "Can [Agent] move from the wall-mounted TV in the Bedroom with pink sheets to the main stairwell opening in the Second floor stair landing and hallway?"
    }
  },
  "SWEEPER": {
    "node_99|node_100": {
      "traversable": false,
      "note": "door sill",
      "timestamp": "2025-11-04T21:38:18.336Z",
      "question": "Can [Agent] move from the BBQ grill area on the Patio and yard to the kitchen island with a sink in the Main living room and kitchen?"
    },
    "node_100|node_101": {
      "traversable": true,
      "note": "",
      "timestamp": "2025-11-04T21:43:35.525Z",
      "question": "Can [Agent] move from the gray sectional sofa in the Main living room and kitchen to the large bed in the Master bedroom?"
    },
    "node_101|node_103": {
      "traversable": true,
      "note": "",
      "timestamp": "2025-11-04T21:43:36.432Z",
      "question": "Can [Agent] move from the gray sectional sofa in the Main living room and kitchen to the large bed in the Master bedroom?"
    },
    "node_100|node_104": {
      "traversable": true,
      "note": "",
      "timestamp": "2025-11-04T21:43:37.512Z",
      "question": "Can [Agent] move from the gray sectional sofa in the Main living room and kitchen to the large bed in the Master bedroom?"
    },
    "node_104|node_105": {
      "traversable": true,
      "note": "",
      "timestamp": "2025-11-04T21:43:40.018Z",
      "question": "Can [Agent] move from the gray sectional sofa in the Main living room and kitchen to the large bed in the Master bedroom?"
    },
    "node_105|node_101": {
      "traversable": true,
      "note": "",
      "timestamp": "2025-11-04T21:43:42.071Z",
      "question": "Can [Agent] move from the gray sectional sofa in the Main living room and kitchen to the large bed in the Master bedroom?"
    },
    "node_101|node_107": {
      "traversable": true,
      "note": "",
      "timestamp": "2025-11-04T21:44:02.723Z",
      "question": "Can [Agent] move from the main double doors in the Entrance foyer and hallway to the computer desk in the Home office next to entrance?"
    },
    "node_103|node_106": {
      "traversable": true,
      "note": "",
      "timestamp": "2025-11-04T21:44:44.297Z",
      "question": "Can [Agent] move from the dresser with a mirror in the Master bedroom to the large corner tub in the Master bedroom bathroom?"
    },
    "node_101|node_105": {
      "traversable": true,
      "note": "",
      "timestamp": "2025-11-04T21:44:55.322Z",
      "question": "Can [Agent] move from the refrigerator in the Main living room and kitchen to the sofa in the Smaller living room with sofa?"
    },
    "node_101|node_108": {
      "traversable": false,
      "note": "cannot go up/down stairs",
      "timestamp": "2025-11-04T21:45:18.508Z",
      "question": "Can [Agent] move from the bottom of the stairs in the Entrance foyer and hallway to the top of the stairs at the Second floor stair landing and hallway?"
    },
    "node_108|node_110": {
      "traversable": true,
      "note": "",
      "timestamp": "2025-11-04T21:45:37.573Z",
      "question": "Can [Agent] move from the central railing on the landing in the Second floor stair landing and hallway to the bed with pink sheets in the Bedroom with pink sheets?"
    },
    "node_109|node_108": {
      "traversable": true,
      "note": "",
      "timestamp": "2025-11-04T21:47:06.197Z",
      "question": "Can [Agent] move from the office chair in the Second floor home office to the bed with stripe sheets in the Bedroom with stripe sheets?"
    },
    "node_108|node_111": {
      "traversable": true,
      "note": "",
      "timestamp": "2025-11-04T21:47:08.158Z",
      "question": "Can [Agent] move from the office chair in the Second floor home office to the bed with stripe sheets in the Bedroom with stripe sheets?"
    },
    "node_115|node_108": {
      "traversable": true,
      "note": "",
      "timestamp": "2025-11-04T21:50:46.335Z",
      "question": "Can [Agent] move from the bed with the gray headboard in the Bedroom with gray wall to the vanity in the Bathroom between two bedrooms?"
    },
    "node_108|node_116": {
      "traversable": true,
      "note": "",
      "timestamp": "2025-11-04T21:50:47.629Z",
      "question": "Can [Agent] move from the bed with the gray headboard in the Bedroom with gray wall to the vanity in the Bathroom between two bedrooms?"
    },
    "node_116|node_114": {
      "traversable": true,
      "note": "",
      "timestamp": "2025-11-04T21:50:48.496Z",
      "question": "Can [Agent] move from the bed with the gray headboard in the Bedroom with gray wall to the vanity in the Bathroom between two bedrooms?"
    },
    "node_115|node_114": {
      "traversable": true,
      "note": "",
      "timestamp": "2025-11-04T21:50:49.683Z",
      "question": "Can [Agent] move from the bed with the gray headboard in the Bedroom with gray wall to the vanity in the Bathroom between two bedrooms?"
    },
    "node_108|node_113": {
      "traversable": true,
      "note": "",
      "timestamp": "2025-11-04T21:52:36.087Z",
      "question": "Can [Agent] move from the office chair in the Second floor home office to the bed with stripe sheets in the Bedroom with stripe sheets?"
    },
    "node_113|node_111": {
      "traversable": false,
      "note": "cannot open door",
      "timestamp": "2025-11-04T21:52:41.314Z",
      "question": "Can [Agent] move from the office chair in the Second floor home office to the bed with stripe sheets in the Bedroom with stripe sheets?"
    },
    "node_111|node_108": {
      "traversable": true,
      "note": "",
      "timestamp": "2025-11-04T21:53:23.912Z",
      "question": "Can [Agent] move from the dresser with a mirror in the Bedroom with stripe sheets to the toilet in the Second floor shared bathroom with red rug?"
    },
    "node_111|node_113": {
      "traversable": false,
      "note": "cannot open door",
      "timestamp": "2025-11-04T21:53:26.512Z",
      "question": "Can [Agent] move from the dresser with a mirror in the Bedroom with stripe sheets to the toilet in the Second floor shared bathroom with red rug?"
    },
    "node_110|node_108": {
      "traversable": true,
      "note": "",
      "timestamp": "2025-11-04T21:53:46.673Z",
      "question": "Can [Agent] move from the wall-mounted TV in the Bedroom with pink sheets to the main stairwell opening in the Second floor stair landing and hallway?"
    }
  },
  "QUADRUPEDAL": {
    "node_99|node_100": {
      "traversable": true,
      "note": "",
      "timestamp": "2025-11-04T21:38:27.215Z",
      "question": "Can [Agent] move from the BBQ grill area on the Patio and yard to the kitchen island with a sink in the Main living room and kitchen?"
    },
    "node_100|node_101": {
      "traversable": true,
      "note": "",
      "timestamp": "2025-11-04T21:43:44.672Z",
      "question": "Can [Agent] move from the gray sectional sofa in the Main living room and kitchen to the large bed in the Master bedroom?"
    },
    "node_101|node_103": {
      "traversable": true,
      "note": "",
      "timestamp": "2025-11-04T21:43:46.352Z",
      "question": "Can [Agent] move from the gray sectional sofa in the Main living room and kitchen to the large bed in the Master bedroom?"
    },
    "node_100|node_104": {
      "traversable": true,
      "note": "",
      "timestamp": "2025-11-04T21:43:47.738Z",
      "question": "Can [Agent] move from the gray sectional sofa in the Main living room and kitchen to the large bed in the Master bedroom?"
    },
    "node_104|node_105": {
      "traversable": true,
      "note": "",
      "timestamp": "2025-11-04T21:43:49.764Z",
      "question": "Can [Agent] move from the gray sectional sofa in the Main living room and kitchen to the large bed in the Master bedroom?"
    },
    "node_105|node_101": {
      "traversable": true,
      "note": "",
      "timestamp": "2025-11-04T21:43:51.363Z",
      "question": "Can [Agent] move from the gray sectional sofa in the Main living room and kitchen to the large bed in the Master bedroom?"
    },
    "node_101|node_107": {
      "traversable": true,
      "note": "",
      "timestamp": "2025-11-04T21:44:03.618Z",
      "question": "Can [Agent] move from the main double doors in the Entrance foyer and hallway to the computer desk in the Home office next to entrance?"
    },
    "node_103|node_106": {
      "traversable": true,
      "note": "",
      "timestamp": "2025-11-04T21:44:45.084Z",
      "question": "Can [Agent] move from the dresser with a mirror in the Master bedroom to the large corner tub in the Master bedroom bathroom?"
    },
    "node_101|node_105": {
      "traversable": true,
      "note": "",
      "timestamp": "2025-11-04T21:44:56.495Z",
      "question": "Can [Agent] move from the refrigerator in the Main living room and kitchen to the sofa in the Smaller living room with sofa?"
    },
    "node_101|node_108": {
      "traversable": true,
      "note": "",
      "timestamp": "2025-11-04T21:45:20.521Z",
      "question": "Can [Agent] move from the bottom of the stairs in the Entrance foyer and hallway to the top of the stairs at the Second floor stair landing and hallway?"
    },
    "node_108|node_110": {
      "traversable": true,
      "note": "",
      "timestamp": "2025-11-04T21:45:38.214Z",
      "question": "Can [Agent] move from the central railing on the landing in the Second floor stair landing and hallway to the bed with pink sheets in the Bedroom with pink sheets?"
    },
    "node_109|node_108": {
      "traversable": true,
      "note": "",
      "timestamp": "2025-11-04T21:47:09.783Z",
      "question": "Can [Agent] move from the office chair in the Second floor home office to the bed with stripe sheets in the Bedroom with stripe sheets?"
    },
    "node_108|node_111": {
      "traversable": true,
      "note": "",
      "timestamp": "2025-11-04T21:47:11.198Z",
      "question": "Can [Agent] move from the office chair in the Second floor home office to the bed with stripe sheets in the Bedroom with stripe sheets?"
    },
    "node_115|node_108": {
      "traversable": true,
      "note": "",
      "timestamp": "2025-11-04T21:50:51.775Z",
      "question": "Can [Agent] move from the bed with the gray headboard in the Bedroom with gray wall to the vanity in the Bathroom between two bedrooms?"
    },
    "node_108|node_116": {
      "traversable": true,
      "note": "",
      "timestamp": "2025-11-04T21:50:53.349Z",
      "question": "Can [Agent] move from the bed with the gray headboard in the Bedroom with gray wall to the vanity in the Bathroom between two bedrooms?"
    },
    "node_116|node_114": {
      "traversable": true,
      "note": "",
      "timestamp": "2025-11-04T21:50:55.269Z",
      "question": "Can [Agent] move from the bed with the gray headboard in the Bedroom with gray wall to the vanity in the Bathroom between two bedrooms?"
    },
    "node_115|node_114": {
      "traversable": true,
      "note": "",
      "timestamp": "2025-11-04T21:50:56.349Z",
      "question": "Can [Agent] move from the bed with the gray headboard in the Bedroom with gray wall to the vanity in the Bathroom between two bedrooms?"
    },
    "node_108|node_113": {
      "traversable": true,
      "note": "",
      "timestamp": "2025-11-04T21:52:46.833Z",
      "question": "Can [Agent] move from the office chair in the Second floor home office to the bed with stripe sheets in the Bedroom with stripe sheets?"
    },
    "node_113|node_111": {
      "traversable": false,
      "note": "cannot open door",
      "timestamp": "2025-11-04T21:52:52.766Z",
      "question": "Can [Agent] move from the office chair in the Second floor home office to the bed with stripe sheets in the Bedroom with stripe sheets?"
    },
    "node_111|node_108": {
      "traversable": true,
      "note": "",
      "timestamp": "2025-11-04T21:53:28.353Z",
      "question": "Can [Agent] move from the dresser with a mirror in the Bedroom with stripe sheets to the toilet in the Second floor shared bathroom with red rug?"
    },
    "node_111|node_113": {
      "traversable": false,
      "note": "cannot open door",
      "timestamp": "2025-11-04T21:53:30.392Z",
      "question": "Can [Agent] move from the dresser with a mirror in the Bedroom with stripe sheets to the toilet in the Second floor shared bathroom with red rug?"
    },
    "node_110|node_108": {
      "traversable": true,
      "note": "",
      "timestamp": "2025-11-04T21:53:47.325Z",
      "question": "Can [Agent] move from the wall-mounted TV in the Bedroom with pink sheets to the main stairwell opening in the Second floor stair landing and hallway?"
    }
  }
}